pureport/__init__.py
pureport/credentials.py
pureport/defaults.py
pureport/exceptions.py
pureport/functions.py
pureport/helpers.py
pureport/models.py
pureport/query.py
pureport/session.py
pureport/transforms.py
pureport/transport.py
test/__init__.py
test/openapi.json
test/requirements.txt
test/models/__init__.py
test/models/test_helpers.py
test/models/test_models.py
test/models/test_models_negative_type.py
test/models/test_models_negative_value.py
test/unit/__init__.py
test/unit/test_credentials.py
test/unit/test_exceptions.py
test/unit/test_functions.py
test/unit/test_helpers.py
test/unit/test_init.py
test/unit/test_model.py
test/unit/test_query.py
test/unit/test_session.py
test/unit/test_transforms.py
test/unit/test_transport.py
test/utils/__init__.py
test/utils/utils.py
pureport_python-0.5.0.dist-info/LICENSE.txt
pureport_python-0.5.0.dist-info/METADATA
pureport_python-0.5.0.dist-info/WHEEL
pureport_python-0.5.0.dist-info/top_level.txt
pureport_python-0.5.0.dist-info/RECORD
