Metadata-Version: 2.1
Name: pureport-python
Version: 0.5.0
Summary: Python library for consuming the Pureport Fabric API
Home-page: https://www.pureport.com
Author: Pureport, Inc
Author-email: info@pureport.com
License: MIT
Project-URL: Documentation, https://pureport-python.readthedocs.io
Project-URL: Code, https://github.com/pureport/pureport-python
Project-URL: Issue tracker, https://github.com/pureport/pureport-python/issues
Keywords: pureport multicloud fabric network cloud automation
Platform: UNKNOWN
Classifier: Environment :: Web Environment
Classifier: Intended Audience :: Developers
Classifier: License :: OSI Approved :: MIT License
Classifier: Operating System :: OS Independent
Classifier: Programming Language :: Python
Classifier: Programming Language :: Python :: 3
Classifier: Programming Language :: Python :: 3.5
Classifier: Programming Language :: Python :: 3.6
Classifier: Programming Language :: Python :: 3.7
Classifier: Programming Language :: Python :: 3.8
Classifier: Programming Language :: Python :: 3.9
Classifier: Programming Language :: Python :: Implementation :: CPython
Classifier: Programming Language :: Python :: Implementation :: PyPy
Classifier: Topic :: Internet
Classifier: Topic :: Internet :: WWW/HTTP
Classifier: Topic :: Software Development :: Libraries
Requires-Python: !=3.0.*, !=3.1.*, !=3.2.*, !=3.3.*, !=3.4.*, <4
Requires-Dist: urllib3
Requires-Dist: pyyaml
